dremel3dpy/__init__.py
dremel3dpy/camera.py
dremel3dpy/helpers/__init__.py
dremel3dpy/helpers/constants.py
dremel3dpy/helpers/timer.py
dremel3dpy-2.1.1.dist-info/LICENSE
dremel3dpy-2.1.1.dist-info/METADATA
dremel3dpy-2.1.1.dist-info/WHEEL
dremel3dpy-2.1.1.dist-info/top_level.txt
dremel3dpy-2.1.1.dist-info/RECORD
